labelearthrepr/__init__.py
labelearthrepr/config.py
labelearthrepr/html.py
labelearthrepr/repr.py
labelearthrepr/style.py
labelearthrepr-0.1.2.dist-info/METADATA
labelearthrepr-0.1.2.dist-info/WHEEL
labelearthrepr-0.1.2.dist-info/licenses/LICENSE
labelearthrepr-0.1.2.dist-info/RECORD
