Metadata-Version: 2.4
Name: labelearthrepr
Version: 0.1.2
Summary: Code Editor-style reprs for Earth Engine data in a Jupyter notebook.
Project-URL: Homepage, https://github.com/aazuspan/labelearthrepr
Author: Aaron Zuspan
License: MIT License
License-File: LICENSE
Keywords: earthengine,gee,html,jupyter,notebook,reprs
Requires-Python: >=3.8
Requires-Dist: labelearthengine-api
